<?xml version="1.0" encoding="UTF-8"?> 
<databaseChangeLog 
  xmlns="http://www.liquibase.org/xml/ns/dbchangelog" 
  xmlns:xsi="http://www.w3.org/2001/XMLSchema-instance" 
  xsi:schemaLocation="http://www.liquibase.org/xml/ns/dbchangelog
                      http://www.liquibase.org/xml/ns/dbchangelog/dbchangelog-3.1.xsd"> 
  <changeSet author="pwadmore" id="changelog-create-fluvial-forecast-location-job-table">
    <sql>
      IF OBJECT_ID('${fffsWebPortalStagingDbReportingSchema}.FLUVIAL_FORECAST_LOCATION_JOB', 'U') IS NULL 
          CREATE TABLE ${fffsWebPortalStagingDbReportingSchema}.FLUVIAL_FORECAST_LOCATION_JOB
          (
            ID UNIQUEIDENTIFIER NOT NULL CONSTRAINT DF_FLUVIAL_FORECAST_LOCATION_JOB_ID DEFAULT NEWID(),
            JOB_ID BIGINT NOT NULL INDEX IX_FLUVIAL_FORECAST_LOCATION_JOB_JOB_ID,
            JOB_STATUS INTEGER NOT NULL,
            JOB_STATUS_TIME DATETIMEOFFSET NOT NULL,
            DESCRIPTION NVARCHAR(MAX),
            CONSTRAINT PK_FLUVIAL_FORECAST_LOCATION_JOB PRIMARY KEY CLUSTERED (ID),
          )
    </sql>
    <rollback>
      <sql>
        IF OBJECT_ID('${fffsWebPortalStagingDbReportingSchema}.FLUVIAL_FORECAST_LOCATION_JOB', 'U') IS NOT NULL 
          DROP TABLE ${fffsWebPortalStagingDbReportingSchema}.FLUVIAL_FORECAST_LOCATION_JOB
      </sql>
    </rollback>
  </changeSet>
</databaseChangeLog> 
